pyacquisition/__init__.py
pyacquisition/py.typed
pyacquisition/core/__init__.py
pyacquisition/core/api_server.py
pyacquisition/core/broadcaster.py
pyacquisition/core/calculations.py
pyacquisition/core/config_parser.py
pyacquisition/core/consumer.py
pyacquisition/core/experiment.py
pyacquisition/core/instrument.py
pyacquisition/core/logging.py
pyacquisition/core/measurement.py
pyacquisition/core/rack.py
pyacquisition/core/relay.py
pyacquisition/core/response.py
pyacquisition/core/scribe.py
pyacquisition/core/adapters/__init__.py
pyacquisition/core/adapters/mock.py
pyacquisition/core/adapters/prologix.py
pyacquisition/core/adapters/pyvisa.py
pyacquisition/core/task_manager/__init__.py
pyacquisition/core/task_manager/task.py
pyacquisition/core/task_manager/task_manager.py
pyacquisition/gui/__init__.py
pyacquisition/gui/api_client.py
pyacquisition/gui/constants.py
pyacquisition/gui/dataframe.py
pyacquisition/gui/openapi.py
pyacquisition/gui/components/__init__.py
pyacquisition/gui/components/endpoint_popup.py
pyacquisition/gui/components/file_window.py
pyacquisition/gui/components/input_group.py
pyacquisition/gui/components/live_data_window.py
pyacquisition/gui/components/live_log_window.py
pyacquisition/gui/components/live_plot.py
pyacquisition/gui/components/task_manager_window.py
pyacquisition/gui/components/inputs/__init__.py
pyacquisition/gui/components/inputs/base_input.py
pyacquisition/gui/components/inputs/boolean_input.py
pyacquisition/gui/components/inputs/enum_input.py
pyacquisition/gui/components/inputs/float_input.py
pyacquisition/gui/components/inputs/integer_input.py
pyacquisition/gui/components/inputs/string_input.py
pyacquisition/gui/components/text/__init__.py
pyacquisition/instruments/__init__.py
pyacquisition/instruments/lakeshore/__init__.py
pyacquisition/instruments/lakeshore/lakeshore_340.py
pyacquisition/instruments/lakeshore/lakeshore_350.py
pyacquisition/instruments/oxford_instruments/__init__.py
pyacquisition-0.1.13.dist-info/METADATA
pyacquisition-0.1.13.dist-info/WHEEL
pyacquisition-0.1.13.dist-info/entry_points.txt
pyacquisition-0.1.13.dist-info/licenses/LICENSE
pyacquisition-0.1.13.dist-info/RECORD
