Metadata-Version: 2.4
Name: pyacquisition
Version: 0.1.13
Summary: Python-based data acquisition
Project-URL: Homepage, https://github.com/jakeayres/pyacquisition
Project-URL: Documentation, https://pyacquisition.readthedocs.io
Project-URL: Repository, https://github.com/jakeayres/pyacquisition.git
Project-URL: Issues, https://github.com/jakeayres/pyacquisition/issues
Author-email: jakeayres <jake_ayres@hotmail.co.uk>
License-File: LICENSE
Requires-Python: >=3.11
Requires-Dist: aiohttp>=3.11.18
Requires-Dist: asyncio>=3.4.3
Requires-Dist: dearpygui>=2.0.0
Requires-Dist: fastapi[standard]>=0.115.12
Requires-Dist: loguru>=0.7.3
Requires-Dist: mkdocs-material>=9.6.11
Requires-Dist: mkdocs>=1.6.1
Requires-Dist: mkdocstrings[python]>=0.29.1
Requires-Dist: pandas>=2.2.3
Requires-Dist: pyserial>=3.5
Requires-Dist: pytest-asyncio>=0.26.0
Requires-Dist: pytest-mock>=3.14.0
Requires-Dist: pytest>=8.3.5
Requires-Dist: pyvisa-py>=0.8.0
Requires-Dist: pyvisa>=1.15.0
Requires-Dist: uvicorn>=0.34.1
